modelicapy/__init__.py
modelicapy/cleanData.py
modelicapy/createUnitScripts.py
modelicapy/gen_dsin.py
modelicapy/getValues.py
modelicapy/parametric.py
modelicapy/read_dslog.py
modelicapy/regressiontest.py
modelicapy/Examples/__init__.py
modelicapy/Graphviz/DepencyGraphGenerator.py
modelicapy/Graphviz/FindMOFiles.py
modelicapy/Graphviz/SearchMOFile.py
modelicapy/Graphviz/__init__.py
modelicapy/raven/__init__.py
modelicapy/raven/simulatePyFMI.py
modelicapy-0.3.2.dist-info/LICENSE.md
modelicapy-0.3.2.dist-info/METADATA
modelicapy-0.3.2.dist-info/WHEEL
modelicapy-0.3.2.dist-info/top_level.txt
modelicapy-0.3.2.dist-info/RECORD
