Metadata-Version: 2.1
Name: modelicapy
Version: 0.3.2
Summary: A Python library containing a variety of scripts and functions for interaction with Modelica and TRANSFORM
Home-page: https://github.com/ORNL-Modelica/ModelicaPy
Author: Scott Greenwood
Author-email: greenwoodms@ornl.gov
License: UT-Battelle Open Source License (Permissive)
Keywords: modelica dymola openmodelica mat
Platform: UNKNOWN
Classifier: Development Status :: 3 - Alpha
Classifier: Environment :: Console
Classifier: License :: Other/Proprietary License
Classifier: Programming Language :: Python :: 2.7
Classifier: Programming Language :: Python :: 3.6
Classifier: Intended Audience :: End Users/Desktop
Classifier: Intended Audience :: Science/Research
Classifier: Topic :: Scientific/Engineering
Classifier: Topic :: Utilities
Requires-Dist: future
